duplication/__init__.py
duplication/minhash_duplication.py
duplication/simhash_duplication.py
duplication/data/test.xlsx
duplication-1.0.2.dist-info/DESCRIPTION.rst
duplication-1.0.2.dist-info/METADATA
duplication-1.0.2.dist-info/RECORD
duplication-1.0.2.dist-info/WHEEL
duplication-1.0.2.dist-info/metadata.json
duplication-1.0.2.dist-info/top_level.txt
