Metadata-Version: 2.0
Name: duplication
Version: 1.0.2
Summary: Python wrapper for de-duplication: natural language processing
Home-page: UNKNOWN
Author: chengtingting
Author-email: 2698641198@qq.com
License: UNKNOWN
Platform: UNKNOWN
